cmdpackage/__init__.py
cmdpackage/main.py
cmdpackage/defs/__init__.py
cmdpackage/defs/createzVirtualEnv.py
cmdpackage/defs/runSubProc.py
cmdpackage/defs/writeCLIPackage.py
cmdpackage/defs/writePyProject.py
cmdpackage/defs/writeSetup.py
cmdpackage/templates/__init__.py
cmdpackage/templates/cmdTemplate.py
cmdpackage/templates/pyprojectTemplate.py
cmdpackage/templates/setupTemplates.py
cmdpackage-0.1.7.dist-info/licenses/LICENSE
cmdpackage-0.1.7.dist-info/METADATA
cmdpackage-0.1.7.dist-info/WHEEL
cmdpackage-0.1.7.dist-info/entry_points.txt
cmdpackage-0.1.7.dist-info/top_level.txt
cmdpackage-0.1.7.dist-info/RECORD
