Metadata-Version: 2.4
Name: cmdpackage
Version: 0.1.7
Summary: Automated python package generator for CLI function calls
Author-email: mpytel <mpytel@domain.com>
Maintainer-email: mpytel <mpytel@domain.com>
Project-URL: Homepage, https://github.com/mpytel/cmdpackage
Project-URL: Bug Tracker, https://github.com/mpytel/cmdpackage/issues
Classifier: Programming Language :: Python
Classifier: Programming Language :: Python :: 3.10
Classifier: Operating System :: OS Independent
License-File: LICENSE
Dynamic: license-file
